README.rst
setup.cfg
setup.py
aipfs/__init__.py
aipfs/transport.py
aipfs.egg-info/PKG-INFO
aipfs.egg-info/SOURCES.txt
aipfs.egg-info/dependency_links.txt
aipfs.egg-info/requires.txt
aipfs.egg-info/top_level.txt
aipfs/api/__init__.py
aipfs/api/bitswap.py
aipfs/api/block.py
aipfs/api/bootstrap.py
aipfs/api/config.py
aipfs/api/dht.py
aipfs/api/diag.py
aipfs/api/file.py
aipfs/api/files.py
aipfs/api/ipfsobject.py
aipfs/api/log.py
aipfs/api/name.py
aipfs/api/pin.py
aipfs/api/refs.py
aipfs/api/repo.py
aipfs/api/stats.py
aipfs/api/swarm.py
aipfs/api/tar.py
test/__init__.py
test/conftest.py
test/test_transport.py
test/test_api/__init__.py
test/test_api/test_bitswap.py
test/test_api/test_block.py
test/test_api/test_bootstrap.py
test/test_api/test_config.py
test/test_api/test_dht.py
test/test_api/test_diag.py
test/test_api/test_file.py
test/test_api/test_files.py
test/test_api/test_ipfs.py
test/test_api/test_log.py
test/test_api/test_name.py
test/test_api/test_object.py
test/test_api/test_pin.py
test/test_api/test_refs.py
test/test_api/test_repo.py
test/test_api/test_stats.py
test/test_api/test_swarm.py
test/test_api/test_tar.py