Metadata-Version: 1.1
Name: aipfs
Version: 0.0.1
Summary: IPFS daemon asyncio client
Home-page: https://github.com/faisalburhanudin/aipfs
Author: faisalburhanufin
Author-email: faisalburhanudin@hotmail.net
License: UNKNOWN
Download-URL: https://github.com/faisalburhanudin/aipfs/archive/0.0.1.tar.gz
Platform: UNKNOWN
